relsys/__init__.py
relsys/model.py
relsys/relsys.cp310-win_amd64.pyd
relsys/relsys.cpython-310-x86_64-linux-gnu.so
relsys-2.2.1.dist-info/LICENSE
relsys-2.2.1.dist-info/METADATA
relsys-2.2.1.dist-info/WHEEL
relsys-2.2.1.dist-info/top_level.txt
relsys-2.2.1.dist-info/RECORD
