Metadata-Version: 2.1
Name: relsys
Version: 2.2.1
Summary: A tool for evaluating a system of queues with finite capacity that are connected through customer relocations.
Author-email: Anders Reenberg Andersen <andersra@live.dk>
Project-URL: Homepage, https://github.com/areenberg/RelSys
Project-URL: Issues, https://github.com/areenberg/RelSys/issues
Classifier: Development Status :: 4 - Beta
Classifier: Programming Language :: Python :: 3
Classifier: License :: OSI Approved :: MIT License
Classifier: Operating System :: OS Independent
Requires-Python: ==3.10
License-File: LICENSE
